{
    "Coeur": {
      "As": "Quel est ton animal préféré et pourquoi ?",
      "2": "Si tu pouvais être un super-héros, qui serais-tu et pourquoi ?",
      "3": "Quelle est ta couleur préférée et qu'est-ce qu'elle représente pour toi ?",
      "4": "Quel est ton dessin animé préféré ?",
      "5": "Si tu pouvais manger un seul plat tous les jours, lequel choisirais-tu ?",
      "6": "Quel est le plus beau cadeau que tu as reçu ?",
      "7": "Si tu pouvais avoir un animal magique, que serait-il ?",
      "8": "Quelle est la chose la plus drôle qui t'est arrivée ?",
      "9": "Quel est ton jeu préféré ?",
      "10": "Si tu pouvais inventer une nouvelle fête, quelle serait-elle ?",
      "Jack": "Quelle est ton activité préférée après l'école ?",
      "Queen": "Quel est ton héros ou ton héroïne dans la vraie vie ?",
      "King": "Si tu pouvais visiter un endroit dans le monde, où irais-tu ?"
    },
    "Carreau": {
      "As": "Si tu pouvais avoir un super pouvoir, lequel choisirais-tu ?",
      "2": "Quelle est ta sucrerie préférée ?",
      "3": "Quel est ton fruit préféré ?",
      "4": "Si tu pouvais devenir un personnage de conte de fées, qui serais-tu ?",
      "5": "Quel métier voudrais-tu faire quand tu seras grand(e) ?",
      "6": "Quelle est la meilleure surprise que tu aimerais recevoir ?",
      "7": "Si tu pouvais être un animal pendant une journée, lequel choisirais-tu ?",
      "8": "Quelle est ta chanson préférée ?",
      "9": "Si tu avais une baguette magique, que ferais-tu en premier ?",
      "10": "Quel est ton endroit préféré pour jouer ?",
      "Jack": "Quel est ton jouet préféré ?",
      "Queen": "Quel est ton livre ou histoire préférée ?",
      "King": "Si tu pouvais voler dans le ciel, où irais-tu en premier ?"
    },
    "Trefles": {
      "As": "Quelle est la chose la plus drôle que tu sais faire ?",
      "2": "Si tu pouvais passer toute une journée à faire une seule chose, que ferais-tu ?",
      "3": "Quel est ton héros préféré dans un film ou une série ?",
      "4": "Quel est ton sport ou activité physique préféré ?",
      "5": "Si tu pouvais inventer une nouvelle règle à l'école, laquelle serait-elle ?",
      "6": "Quel est le prénom de ton meilleur ami ou de ta meilleure amie ?",
      "7": "Quel est ton endroit préféré à la maison ?",
      "8": "Si tu pouvais transformer une chose ordinaire en quelque chose de magique, laquelle choisirais-tu ?",
      "9": "Quel est ton dessert préféré ?",
      "10": "Si tu pouvais jouer dans un film, quel rôle aimerais-tu avoir ?",
      "Jack": "Quelle est la blague la plus drôle que tu connais ?",
      "Queen": "Quelle est la chose que tu adores apprendre à l'école ?",
      "King": "Si tu pouvais choisir un animal pour te tenir compagnie en classe, lequel serait-il ?"
    },
    "Piques": {
      "As": "Si tu pouvais construire la maison de tes rêves, comment serait-elle ?",
      "2": "Quel est ton personnage préféré dans un jeu vidéo ?",
      "3": "Quelle est la chose la plus courageuse que tu as faite ?",
      "4": "Si tu pouvais être invisible pendant une journée, que ferais-tu ?",
      "5": "Quelle est la chose que tu fais le mieux ?",
      "6": "Quel est ton plus grand rêve ?",
      "7": "Si tu pouvais avoir un parc d’attractions entier pour toi tout seul, que ferais-tu ?",
      "8": "Si tu pouvais inventer un nouveau jouet, comment serait-il ?",
      "9": "Quel est ton endroit préféré pour faire des câlins ?",
      "10": "Si tu pouvais parler à un animal, lequel choisirais-tu ?",
      "Jack": "Quel est ton repas préféré du soir ?",
      "Queen": "Si tu pouvais choisir un animal pour être ton meilleur ami, lequel serait-ce ?",
      "King": "Quelle est ta meilleure aventure avec tes amis ?"
    },
    "Jokers": {
      "Red": "Si tu pouvais faire un souhait qui se réalise maintenant, que souhaiterais-tu ?",
      "Black": "Si tu pouvais passer une journée entière avec ton personnage préféré, qui serait-ce ?"
    }
  }
  